xia_service_cloudflare/__init__.py
xia_service_cloudflare/engine.cp311-win_amd64.pyd
xia_service_cloudflare/service.cp311-win_amd64.pyd
xia_service_cloudflare-0.0.7.dist-info/LICENSE.txt
xia_service_cloudflare-0.0.7.dist-info/METADATA
xia_service_cloudflare-0.0.7.dist-info/WHEEL
xia_service_cloudflare-0.0.7.dist-info/top_level.txt
xia_service_cloudflare-0.0.7.dist-info/RECORD
